[
    {
        "day": "Monday",
        "AM": "ESOL",
        "earlyPM": "NO CLASSES",
        "latePM": "NO CLASSES",
        "evening": "ESOL",
        "lateEvening": "Chess Club"
    },
    {
        "day": "Tuesday",
        "AM": "ESOL | Voice Class, Perth Theatre",
        "earlyPM": "NO CLASSES",
        "latePM": "Guitar Class",
        "evening": "ESOL",
        "lateEvening": ""
    },
    {
        "day": "Wednesday",
        "AM": "ESOL",
        "earlyPM": "Speakers' Club",
        "latePM": "NO CLASSES",
        "evening": "ESOL",
        "lateEvening": ""
    },
    {
        "day": "Thursday",
        "AM": "ESOL",
        "earlyPM": "Table Tennis Club",
        "latePM": "Table Tennis",
        "evening": "ESOL",
        "lateEvening": "Speakers' Club (alternate weeks)"
    },
    {
        "day": "Friday",
        "AM": "ADMIN",
        "earlyPM": "NO CLASSES",
        "latePM": "NO CLASSES",
        "evening": "NO CLASSES",
        "lateEvening": ""
    },
    {
        "day": "Saturday",
        "AM": "ESOL | Children's Club",
        "earlyPM": "NO CLASSES",
        "latePM": "NO CLASSES",
        "evening": "NO CLASSES",
        "lateEvening": ""
    },
    {
        "day": "Sunday",
        "AM": "ESOL",
        "earlyPM": "NO CLASSES",
        "latePM": "NO CLASSES",
        "evening": "NO CLASSES",
        "lateEvening": ""
    }
]